{
    "menu": {
        "orders": "Danh sách đơn",
        "operate": "Vận hành",
        "customer": "Khách hàng",
        "complaint": "Khiếu nại",
        "finance": "Tài chính",
        "system": "Hệ thống",
        "packages": "Danh sách kiện",
        "delivery": "Danh sách YCG"
    },
    "message": {
        "503": "Máy chủ không khả dụng, vui lòng thử lại sau ít phút",
        "network_error": "Vui lòng kiểm tra lại kết nối mạng và thử lại",
        "authenticating": "Đang xác thực. Vui lòng đợi trong giây lát",
        "welcome": "Xin chào {{username}}. Bạn sẽ được chuyển về trang chủ trong giây lát.",
        "try_again": "Không thể kết nối tới máy chủ. Vui lòng thử lại sau",
        "loading": "Đang tải",
        "edit_price_sucess": "Thay đổi đơn giá thành công",
        "title_failed": "Thất bại",
        "edit_price_failed": "Thay đổi đơn giá thất bại",
        "no_data": "Không có dữ liệu",
        "no_order": "Danh sách đơn hàng trống",
        "not_found_order": "Không tìm thấy đơn hàng phù hợp",
        "edit_quantity_sucess": "Thay đổi số lượng Mua/Nhận của sản phẩm thành công",
        "edit_quantity_failed": "Thay đổi số lượng Mua/Nhận của sản phẩm thất bại",
        "Internal Server Error": "Xảy ra lỗi. Vui lòng thử lại",
        "Constraint Violation": "Dữ liệu không hợp lệ",
        "Bad Request": "Dữ liệu không hợp lệ",
        "edit_staff_remark_sucess": "Thay đổi ghi chú của nhân viên thành công",
        "duplicate_code": "{{attribute}} đã tồn tại trên hệ thống",
        "not_found": "Không tìm thấy bản ghi phù hợp",
        "cannot_delete_tracking": "Không thể xóa mã vận đơn vì đang có kiện hàng đang sử dụng mã vận đơn này"
    },
    "orders": {
        "orders_empty": "Chưa có dữ liệu",
        "search_order_no_data": "Không tìm thấy kết quả phù hợp",
        "title_list": "Danh sách đơn hàng",
        "title_page": "Quản lý đơn hàng",
        "export_csv": "Xuất CSV",
        "quantity_check": "Số lượng đặt / mua / nhận",
        "merchant": "Người bán",
        "purchasing_staff": "Nhân viên mua hàng",
        "amount": "Giá bán",
        "created_at": "Thời gian tạo đơn",
        "net_weight": "Cân nặng tịnh",
        "fee_weight": "Cân nặng tính phí VCQT",
        "purchasing_account": "Tài khoản mua hàng"
    },
    "order": {
        "filter_by": "Tìm theo",
        "filter_by_order_id": "Mã đơn hàng/ID đơn hàng",
        "filter_origin_order_code": "Mã hóa đơn gốc",
        "filter_buyer": "Tài khoản mua hàng",
        "filter_order_logistic": "Mã vận đơn",
        "filter_customer": "Nhập thông tin khách hàng:",
        "filter_by_time": "Thời gian:",
        "btn_filter": "Tìm kiếm",
        "service": "Dịch vụ:"
    },
    "order_filter": {
        "status": "Trạng thái đơn",
        "actions": "Hành động",
        "refresh": "Làm mới bộ lọc"
    },
    "receipt_address": {
        "success": "Sửa địa chỉ nhận thành công"
    },
    "order_info": {
        "order_detail": "Chi tiết đơn hàng",
        "price": "Giá bán",
        "order_list": "Danh sách đơn hàng",
        "edit": "Sửa",
        "total_goods_value": "Tổng tiền hàng",
        "merchant_contacts": "Liên hệ người bán",
        "customer_code": "Mã khách hàng",
        "purchasing_account": "Tài khoản mua hàng",
        "net_weight": "Cân nặng tịnh",
        "destination_warehouse": "Kho phân phối",
        "receiving_warehouse": "Kho nhận",
        "purchasing_staff": "Nhân viên mua hàng",
        "convert_weight": "Cân nặng quy đổi",
        "emd_mount": "Tỉ lệ đặt cọc",
        "cost_weight": "Cân tính phí",
        "origin_bill": "Hoá đơn gốc",
        "expand_content": "Mở rộng thông tin",
        "shrink_content": "Thu gọn thông tin",
        "service": "Dịch vụ",
        "address": "Địa chỉ nhận hàng",
        "customer_address_note": "Ghi chú",
        "member": "Thành viên",
        "aliwang": "Tài khoản aliwangwang",
        "merchant": "Người bán",
        "edit_status_success": "Sửa trạng thái đơn hàng thành công",
        "edit_status_failed": "Sửa trạng thái đơn hàng thất bại",
        "add_original_receipt_success": "Thêm mã hóa đơn gốc thành công",
        "delete_original_receipt_success": "Xóa mã hóa đơn gốc thành công",
        "delete_original_receipt_failed": "Xóa mã hóa đơn gốc thất bại",
        "update_success": "Cập nhật thông tin đơn thành công",
        "update_failed": "Cập nhật thông tin đơn thất bại"
    },
    "order_original_receipt": {
        "add_failed": "Thêm mã hóa đơn gốc thất bại",
        "message.duplicate_code": "Mã hõa đơn đã tồn tại trên đơn",
        "add_title": "Thêm hóa đơn",
        "list": "Danh sách hóa đơn",
        "update_delete_btn": "Cập nhật thay đổi",
        "cancel_btn": "Hủy",
        "edit_modal_title": "Chỉnh sửa hóa đơn gốc",
        "no_data": "Chưa có dữ liệu"
    },
    "order_detail": {
        "tab_product": "Sản phẩm",
        "tab_transport": "Vận chuyển",
        "tab_finance": "Phí đơn hàng",
        "tab_trade": "Giao dịch",
        "tab_history": "Lịch sử đơn hàng",
        "service": "Dịch vụ"
    },
    "order_detail_product": {
        "title_table": "Sản phẩm",
        "price": "Đơn giá",
        "total": "Tổng tiền",
        "export_csv": "Xuất CSV",
        "bt_buy_enough": "Mua đủ",
        "bt_receive_enough": "Nhận đủ",
        "title_language": "Đổi ngôn ngữ",
        "title_quantity": "Đặt/Mua/Nhận",
        "title_popup_edit_price": "Thay đổi đơn giá",
        "title_popup_edit_quantity": "Thay đổi số lượng",
        "purchase_quantity": "Số lượng mua",
        "receice_quantity": "Số lượng nhận",
        "chat_private": "Chat nội bộ về SP",
        "chat_note": "Ghi chú cho SP",
        "title_remark": "Ghi chú của khách",
        "title_staff_remark": "Ghi chú của nhân viên"
    },
    "comment_internal": {
        "tab_all": "Tất cả",
        "tab_comment": "Trao đổi",
        "tab_log": "Log",
        "title": "Trao đổi nội bộ",
        "bt_send": "Gửi"
    },
    "status": {
        "ACCEPTED": "Chưa mua",
        "PENDING_PURCHASING": "Chưa mua",
        "DEPOSITED": "Đã đặt cọc",
        "WAITING_FOR_PAYMENT": "Chờ thanh toán",
        "WAIT_FOR_APPROVE": "Chờ duyệt",
        "CUSTOMER_RECEIVED": "Khách nhận",
        "PURCHASED": "Đã mua hàng",
        "TRANSPORTING": "Vận chuyển",
        "MIA": "Thất lạc",
        "CANCELLED": "Hủy bỏ",
        "WAIT_FOR_DELIVERY": "Sẵn sàng giao",
        "OUT_OF_STOCK": "Hết hàng",
        "REQUEST_FOR_DELIVERY": "Yêu cầu giao",
        "RECEIVED": "Nhập hàng nhận",
        "MERCHANT_DELIVERING": "Người bán giao",
        "PURCHASING": "Đang mua",
        "ORDERED": "Đã đặt hàng",
        "DELIVERING": "Đang giao",
        "PENDING": "Chờ xác nhận",
        "PUTAWAY": "Kiện về kho",
        "REQUESTED": "Yêu cầu giao",
        "DELIVERED": "Khách nhận",
        "MISSING": "Thất lạc",
        "WAITING": "Chờ giao",
        "READY_FOR_DELIVERY": "Sẵn sàng giao"
    },
    "order_address": {
        "fullname": "Họ tên",
        "phone": "Điện thoại",
        "province": "Thành phố",
        "district": "Quận / Huyện",
        "detail": "Địa chỉ",
        "note": "Ghi chú",
        "edit_success": "Sửa địa chỉ nhận hàng thành công",
        "edit_failed": "Sửa địa chỉ nhận hàng thất bại",
        "edit_title_form": "Sửa địa chỉ nhận hàng",
        "btn_update_modal": "Sửa địa chỉ",
        "btn_cancel_modal": "Thoát"
    },
    "notification": {
        "title_failed": "Thất bại"
    },
    "validation": {
        "required": "{{attribute}} là bắt buộc",
        "max": "{{attribute}} không được lớn hơn {{max}} ký tự",
        "min": "{{attribute}} phải có ít nhất {{min}} ký tự",
        "regex": "{{attribute}} không hợp lệ",
        "max_value": "{{attribute}} không được lớn hơn {{max}}",
        "confirm_password": "{{attribute}} không khớp {{value}}"
    },
    "button": {
        "save": "Đồng ý",
        "cancel": "Bỏ qua"
    },
    "comment": {
        "placeholder": "Trao đổi với khách hàng",
        "send": "Gửi",
        "comment_failed": "Trao đổi thất bại",
        "max_size_message": "Bạn chỉ có thể gửi tệp dưới 10M",
        "only_image": "Bạn chỉ có thể gửi tệp ảnh",
        "max": "Bạn chỉ có thể gửi tối đa 10 tệp",
        "comment_empty": "Chưa có trao đổi với khách hàng"
    },
    "btn": {
        "try_again": "Thử lại"
    },
    "tab_transport": {
        "shipping_code": "Mã vận đơn",
        "package_code": "Mã kiện",
        "order_tran_code": "Mã vận đơn",
        "status": "Trạng thái",
        "volume": "Thể tích",
        "weight": "Cân nặng",
        "last_update": "Cập nhật lần cuối",
        "add_package": "Thêm kiện hàng",
        "cancel_add": "Hủy",
        "create_package": "Tạo",
        "received": "Đã nhận",
        "require_ship": "Yêu cầu giao",
        "wait": "Chờ giao",
        "shipping": "Đang giao",
        "transport": "Vận chuyển",
        "goods_received": "Nhập hàng nhận",
        "lost": "Thất lạc",
        "new_tag": "Thêm mã vận đơn",
        "create_package_failed": "Tạo kiện hàng thất bại",
        "create_package_success": "Tạo kiện hàng thành công",
        "delete_package_success": "Xoá kiện hàng thành công",
        "delete_package_failed": "Xoá kiện hàng thất bại",
        "update_package_success": "Cập nhật thành công",
        "update_package_failed": "Cập nhật thất bại",
        "create_OTCode_success": "Tạo mã vận đơn thành công",
        "create_OTCode_failed": "Tạo mã vận đơn thất bại",
        "delete_OTCode_success": "Xoá mã vận đơn thành công",
        "delete_OTCode_failed": "Xoá mã vận đơn thất bại",
        "create_duplicated_OTCode_failed": "Mã vận đơn đã tồn tại",
        "select_tracking": "Chọn mã",
        "confirm_delete_package": "Xác nhận xoá kiện hàng",
        "confirm_delete_tracking": "Xác nhận xoá mã vận đơn",
        "ques_package": "Bạn có chắc chắn xoá kiện hàng {{name}} ?",
        "ques_tracking": "Bạn có chắc chắn xoá mã vận đơn {{name}} ?"
    },
    "fee": {
        "edit_fee": "Sửa",
        "fee_empty": "Chưa có bảng phí",
        "add_other_fee": "Thêm phụ phí",
        "free": "Miễn phí",
        "formula_amount": "Tiền công thức",
        "fee_name": "Tên loại phí",
        "other_fee": "Phí khác",
        "handle_amount": "Tiền tính tay",
        "service_fee": "Phí dịch vụ",
        "delivery_fee": "Phí vận chuyển",
        "payment_fee": "Thanh toán",
        "change_fee_title": "Thay đổi {{name}}",
        "reason_change": "Lí do thay đổi phí",
        "deposit": "Đặt cọc",
        "total": "Tổng thanh toán",
        "refund": "Trả lại",
        "refund_complaint": "Trả lại từ KNDV",
        "arrears": "Còn thiếu",
        "edit_success": "Thay đổi phí thành công",
        "edit_failed": "Thay đổi phí thất bại",
        "missing_reason": "Lý do bắt buộc khi thay đổi phí",
        "add_title": "Thêm phí mới",
        "choice_fee": "Chọn loại phí",
        "reason_fee": "Lý do",
        "btn_add": "Thêm phí mới",
        "btn_cancel": "Hủy",
        "money": "Nhập số tiền"
    },
    "order_service": {
        "title_popup": "Lựa chọn dịch vụ",
        "bt_cancel": "Hủy",
        "bt_submit": "Xác nhận",
        "msg_edit_fail": "Vui lòng thử lại",
        "msg_edit_success": "Sửa dịch vụ thành công"
    },
    "trade": {
        "transaction-title": "Lịch sử giao dịch",
        "time": "Thời gian",
        "amount": "Giá trị",
        "type": "Loại giao dịch",
        "description": "Mô tả",
        "transaction_empty": "Lịch sử giao \bdịch trống"
    },
    "package": {
        "packages_header": "Danh sách kiện hàng",
        "packages_title": "Kiện hàng",
        "code": "Mã Kiện",
        "tracking_number": "Mã vận đơn",
        "status": "Trạng thái",
        "order_code": "Mã đơn hàng",
        "volumetric": "Thể tích",
        "no_identify": "Chưa xác định",
        "customer": "Thông tin khách hàng",
        "weight": "Cân nặng",
        "package_status": "Trạng thái kiện hàng",
        "create_pack": "Tạo kiện",
        "filter_by": "Tìm theo",
        "pack_code": "Mã kiện...",
        "tracking_code": "Mã vận đơn...",
        "package_empty": "Danh sách kiện trống",
        "customer_code": "Khách hàng/ Mã khách",
        "refresh_filter": "Làm mới bộ lọc",
        "search": "TÌM KIẾM"
    },
    "delivery_request": {
        "code": "Mã phiếu",
        "customer": "Thông tin khách hàng",
        "created_at": "Ngày tạo",
        "status": "Trạng thái",
        "address": "Địa chỉ",
        "package_created_at": "Ngày tạo",
        "package_volume": "Thể tích",
        "package_weight": "Cân nặng",
        "title": "Danh sách yêu cầu giao",
        "not_found": "Không tìm thấy phiếu giao phù hợp",
        "menu": "Yêu cầu giao",
        "not_found_package": "Không tìm thấy kiện phù hợp"
    },
    "delivery": {
        "request": "Yêu cầu giao",
        "created_at": "Ngày tạo",
        "total_weight": "Tổng cân nặng",
        "delivery_package": "Danh sách kiện",
        "log": "Log",
        "address": "Địa chỉ giao hàng",
        "cod_amount": "Tiền COD",
        "total": "Tổng tiền",
        "delivery_title": "Chi tiết Yêu cầu giao",
        "delivery_list": "Danh sách yêu cầu",
        "empty_package": "Không có dữ liệu",
        "order_code": "Mã đơn hàng",
        "package_code": "Mã kiện",
        "take_delivery": "Yêu cầu giao",
        "weight": "Cân nặng",
        "volume": "Thể tích",
        "createdAt": "Ngày tạo"
    },
    "log_product": {
        "purchasedQuantity": "<strong>{{name}}</strong> đã cập nhật số lượng mua từ <strong>{{oldValue}}</strong> thành <strong>{{newValue}}</strong>",
        "receivedQuantity": "<strong>{{name}}</strong> đã cập nhật số lượng nhận từ <strong>{{oldValue}}</strong> thành <strong>{{newValue}}</strong>",
        "actualPrice": "<strong>{{name}}</strong> đã cập nhật giá sản phẩm từ <strong>{{oldValue}}¥</strong> thành <strong>{{newValue}}¥</strong>",
        "staffRemark": "<strong>{{name}}</strong> đã cập nhật ghi chú của nhân viên từ <strong>{{oldValue}}</strong> thành <strong>{{newValue}}</strong>",
        "remark": "<strong>{{name}}</strong> đã cập nhật ghi chú của khách hàng từ <strong>{{oldValue}}</strong> thành <strong>{{newValue}}</strong>",
        "update_history": "Lịch sử cập nhật"
    }
}